pydatpiff/__init__.py
pydatpiff/constants.py
pydatpiff/errors.py
pydatpiff/media.py
pydatpiff/mixtapes.py
pydatpiff/urls.py
pydatpiff/backend/__init__.py
pydatpiff/backend/mediasetup.py
pydatpiff/backend/scraper.py
pydatpiff/backend/audio/__init__.py
pydatpiff/backend/audio/audio_engine.py
pydatpiff/backend/audio/baseplayer.py
pydatpiff/backend/audio/mpvplayer.py
pydatpiff/backend/audio/player.py
pydatpiff/backend/audio/vlcplayer.py
pydatpiff/frontend/__init__.py
pydatpiff/frontend/screen.py
pydatpiff/utils/.logging_config.yaml
pydatpiff/utils/__init__.py
pydatpiff/utils/filehandler.py
pydatpiff/utils/logging.py
pydatpiff/utils/request.py
pydatpiff/utils/utils.py
pydatpiff-2.1.0.dist-info/LICENSE
pydatpiff-2.1.0.dist-info/METADATA
pydatpiff-2.1.0.dist-info/WHEEL
pydatpiff-2.1.0.dist-info/entry_points.txt
pydatpiff-2.1.0.dist-info/top_level.txt
pydatpiff-2.1.0.dist-info/RECORD
